TravelSuLib/TravelSu.py
TravelSuLib/__init__.py
travelinslib-0.0.6.dist-info/METADATA
travelinslib-0.0.6.dist-info/WHEEL
travelinslib-0.0.6.dist-info/licenses/LICENSE
travelinslib-0.0.6.dist-info/RECORD
