Metadata-Version: 2.3
Name: TravelInsLib
Version: 0.0.6
Summary: A small example package
Project-URL: Homepage, https://github.com/Abdu-AJ/TravelInsuranceLib.git
Project-URL: Bug Tracker, https://github.com/Abdu-AJ/TravelInsuranceLib.git
Author-email: AbdulJalil <x22241388@student.ncirl.ie>
License-Expression: MIT
License-File: LICENSE
Classifier: License :: OSI Approved :: MIT License
Classifier: Operating System :: OS Independent
Classifier: Programming Language :: Python :: 3
Requires-Python: >=3.7
Requires-Dist: requests>=2.25.1
